{
  "events": [
    {
      "eventType": "Anchored",
      "startTime": "2025-08-23 05:00:00",
      "endTime": "2025-08-23 05:30:00",
      "duration": 0.5,
      "location": "outer anchorage",
      "description": "Vessel anchored at outer anchorage",
      "confidence": 1.0,
      "rawText": "23 Aug 2025 05:00 - Vessel anchored at outer anchorage",
      "context": {
        "cargo_type": null,
        "quantity": null,
        "weather": null,
        "delays": [],
        "personnel": []
      }
    },
    {
      "eventType": "Arrived",
      "startTime": "2025-08-23 05:30:00",
      "endTime": "2025-08-23 06:00:00",
      "duration": 0.5,
      "location": "port limits",
      "description": "Vessel arrived at port limits",
      "confidence": 1.0,
      "rawText": "23 Aug 2025 05:30 - Vessel arrived at port limits",
      "context": {
        "cargo_type": null,
        "quantity": null,
        "weather": null,
        "delays": [],
        "personnel": []
      }
    }
  ],
  "vesselInfo": {
    "name": "Mv Test Vessel\nPort",
    "imo": "IMO1234567",
    "flag": "Panama"
  },
  "portInfo": {
    "name": "Singapore\n\n23 Aug 2025 05",
    "country": "Singapore"
  },
  "totalLaytime": "1.0 hours",
  "statistics": {
    "total_events": 2,
    "total_duration_hours": 1.0,
    "event_types": {
      "Anchored": {
        "count": 1,
        "total_duration": 0.5
      },
      "Arrived": {
        "count": 1,
        "total_duration": 0.5
      }
    },
    "average_event_duration": 0.5
  },
  "documentDate": "2025-08-23",
  "extractedFrom": "specific_overlap_test.txt",
  "totalEvents": 2,
  "extractionTimestamp": "2025-08-23T12:59:34.395147"
}